<?xml version="1.0" ?><annotation>
	<folder>500aCrop</folder>
	<filename>selecionadasDiaACrop443Augmented.jpg</filename>
	<path>D:\Users\guilh\PycharmProjects\testingAugmentation\Selecionadas Dia Crop\500aCrop\selecionadasDiaACrop443.jpg</path>
	<source>
		<database>Unknown</database>
	</source>
	<size>
		<width>746</width>
		<height>560</height>
		<depth>3</depth>
	</size>
	<segmented>0</segmented>
	<object>
		<name>person</name>
		<pose>Unspecified</pose>
		<truncated>0</truncated>
		<difficult>0</difficult>
		<bndbox>
			<xmin>661</xmin>
			<ymin>301</ymin>
			<xmax>719</xmax>
			<ymax>453</ymax>
		</bndbox>
	</object>
</annotation>