<annotation>
	<folder>500bCrop</folder>
	<filename>selecionadasDiaBCrop80.jpg</filename>
	<path>C:\Users\giova\Documents\TCC\images3\labelImg-master\labelImg-master\dist\500bCrop\selecionadasDiaBCrop80.jpg</path>
	<source>
		<database>Unknown</database>
	</source>
	<size>
		<width>746</width>
		<height>560</height>
		<depth>3</depth>
	</size>
	<segmented>0</segmented>
	<object>
		<name>person</name>
		<pose>Unspecified</pose>
		<truncated>0</truncated>
		<difficult>0</difficult>
		<bndbox>
			<xmin>131</xmin>
			<ymin>123</ymin>
			<xmax>157</xmax>
			<ymax>196</ymax>
		</bndbox>
	</object>
	<object>
		<name>person</name>
		<pose>Unspecified</pose>
		<truncated>0</truncated>
		<difficult>0</difficult>
		<bndbox>
			<xmin>160</xmin>
			<ymin>84</ymin>
			<xmax>185</xmax>
			<ymax>107</ymax>
		</bndbox>
	</object>
</annotation>
